{
  "generated_at": "2026-02-10T01:45:30.830919+08:00",
  "total_titles_processed": 315,
  "failed_sources": [],
  "trends": [
    {
      "keyword_group": "特朗普",
      "match_count": 3,
      "titles": [
        {
          "title": "以“和平”为名：特朗普调停冲突，意在关键矿产？",
          "url": "https://m.thepaper.cn/newsDetail_forward_32551636",
          "source": "澎湃新闻",
          "ranks": [
            6
          ],
          "is_new": false,
          "appearance_count": 1,
          "time_info": "01时45分"
        },
        {
          "title": "美民调：多数人不认可特朗普关税政策",
          "url": "https://www.toutiao.com/trending/7604360239181807658/",
          "source": "今日头条",
          "ranks": [
            19
          ],
          "is_new": false,
          "appearance_count": 1,
          "time_info": "01时45分"
        },
        {
          "title": "美国汽车工人联合会：1月13日冲撞美国总统特朗普的工人未受纪律处分，仍保留工作。",
          "url": "https://flash.jin10.com/detail/20260210003111533800",
          "source": "金十数据",
          "ranks": [
            30
          ],
          "is_new": false,
          "appearance_count": 1,
          "time_info": "01时45分"
        }
      ]
    }
  ],
  "report_image_url": "https://joyce677.github.io/TrendRadar/img/news.jpg"
}